odoo/addons/stock_move_value_report/README.rst
odoo/addons/stock_move_value_report/__init__.py
odoo/addons/stock_move_value_report/__manifest__.py
odoo/addons/stock_move_value_report/i18n/es.po
odoo/addons/stock_move_value_report/i18n/fr.po
odoo/addons/stock_move_value_report/i18n/it.po
odoo/addons/stock_move_value_report/i18n/pt.po
odoo/addons/stock_move_value_report/i18n/stock_move_value_report.pot
odoo/addons/stock_move_value_report/readme/CONTRIBUTORS.md
odoo/addons/stock_move_value_report/readme/DESCRIPTION.md
odoo/addons/stock_move_value_report/readme/USAGE.md
odoo/addons/stock_move_value_report/report/stock_inventory_value_report.xml
odoo/addons/stock_move_value_report/report/stock_move_line_value_report.xml
odoo/addons/stock_move_value_report/report/stock_move_value_report.xml
odoo/addons/stock_move_value_report/report/stock_picking_value_report.xml
odoo/addons/stock_move_value_report/report/stock_scrap_value_report.xml
odoo/addons/stock_move_value_report/report/stock_value_report.xml
odoo/addons/stock_move_value_report/static/description/icon.png
odoo/addons/stock_move_value_report/static/description/index.html
odoo_addon_stock_move_value_report-18.0.1.0.0.2.dist-info/METADATA
odoo_addon_stock_move_value_report-18.0.1.0.0.2.dist-info/WHEEL
odoo_addon_stock_move_value_report-18.0.1.0.0.2.dist-info/top_level.txt
odoo_addon_stock_move_value_report-18.0.1.0.0.2.dist-info/RECORD
